urlock/__init__.py
urlock/urlock.py
urlock-0.1.22.dist-info/LICENSE.txt
urlock-0.1.22.dist-info/METADATA
urlock-0.1.22.dist-info/WHEEL
urlock-0.1.22.dist-info/top_level.txt
urlock-0.1.22.dist-info/RECORD
