Metadata-Version: 2.1
Name: urlock
Version: 0.1.22
Summary: Library for talking to a running Urbit ship
Home-page: http://github.com/baudtack/urlock-py
Author: David Kerschner
Author-email: dkerschner@gmail.com
License: MIT
Keywords: urbit urlock
Platform: UNKNOWN
Requires-Dist: requests
Requires-Dist: sseclient-py
